sl_forgery/__init__.py
sl_forgery/py.typed
sl_forgery/analysis/__init__.py
sl_forgery/analysis/bleaching_check.py
sl_forgery/analysis/create_manifest.py
sl_forgery/analysis/example_filter.yaml
sl_forgery/analysis/example_workflow.ipynb
sl_forgery/analysis/place_1d.py
sl_forgery/analysis/plotting.py
sl_forgery/analysis/processing.py
sl_forgery/analysis/temp.ipynb
sl_forgery/analysis/tm6_filter.yaml
sl_forgery/command_line_interfaces/__init__.py
sl_forgery/command_line_interfaces/execute.py
sl_forgery/command_line_interfaces/process.py
sl_forgery/command_line_interfaces/project.py
sl_forgery/command_line_interfaces/server.py
sl_forgery/forging/__init__.py
sl_forgery/forging/data_assembly.py
sl_forgery/forging/dataset.py
sl_forgery/forging/forging.py
sl_forgery/forging/suite2p_multiday.py
sl_forgery/managing/__init__.py
sl_forgery/managing/interface.py
sl_forgery/managing/processing.py
sl_forgery/processing/__init__.py
sl_forgery/processing/interface.py
sl_forgery/server/__init__.py
sl_forgery/server/job.py
sl_forgery/server/pipeline.py
sl_forgery/server/server.py
sl_forgery/shared_assets/__init__.py
sl_forgery/shared_assets/metadata.py
sl_forgery/shared_assets/pipelines.py
sl_forgery/shared_assets/utilities.py
sl_forgery-1.0.0rc2.dist-info/METADATA
sl_forgery-1.0.0rc2.dist-info/WHEEL
sl_forgery-1.0.0rc2.dist-info/entry_points.txt
sl_forgery-1.0.0rc2.dist-info/licenses/LICENSE
sl_forgery-1.0.0rc2.dist-info/RECORD
