Metadata-Version: 2.4
Name: sl-forgery
Version: 1.0.0rc2
Summary: Provides tools for processing and managing the data acquired in the Sun (NeuroAI) lab.
Project-URL: Homepage, https://github.com/Sun-Lab-NBB/sl-forgery
Project-URL: Documentation, https://sl-forgery-api-docs.netlify.app/
Author: Ivan Kondratyev, Kushaan Gupta
Maintainer-email: Ivan Kondratyev <ik278@cornell.edu>
License:                     GNU GENERAL PUBLIC LICENSE
License-File: LICENSE
Keywords: data,dataset,processing,sunlab
Classifier: Development Status :: 5 - Production/Stable
Classifier: Intended Audience :: Developers
Classifier: License :: OSI Approved :: GNU General Public License v3 or later (GPLv3+)
Classifier: Operating System :: OS Independent
Classifier: Programming Language :: Python :: 3.13
Classifier: Topic :: Scientific/Engineering :: Bio-Informatics
Classifier: Typing :: Typed
Requires-Python: <3.15,>=3.14
Requires-Dist: appdirs<2,>=1
Requires-Dist: ataraxis-base-utilities<6,>=5
Requires-Dist: ataraxis-data-structures<6,>=5
Requires-Dist: ataraxis-time<6,>=5
Requires-Dist: filelock<4,>=3
Requires-Dist: matplotlib<4,>=3
Requires-Dist: natsort-rs<1,>=0
Requires-Dist: numba<1,>=0.63.0rc1
Requires-Dist: numpy<3,>=2
Requires-Dist: paramiko<5,>=4
Requires-Dist: plotly<7,>=6
Requires-Dist: polars<2,>=1
Requires-Dist: pyarrow<23,>=22
Requires-Dist: pyqt6<7,>=6
Requires-Dist: pytz<2026,>=2025
Requires-Dist: scipy<2,>=1
Requires-Dist: simple-slurm<1,>=0
Requires-Dist: sl-shared-assets<7,>=6.0.1rc9
Requires-Dist: tabulate<1,>=0
Requires-Dist: tqdm<5,>=4
Requires-Dist: umap-learn<1,>=0.5.9.post2
Requires-Dist: xxhash<4,>=3
Provides-Extra: dev
Requires-Dist: ataraxis-automation<8,>=7; extra == 'dev'
Requires-Dist: tox-uv<2,>=1; extra == 'dev'
Requires-Dist: tox<5,>=4; extra == 'dev'
Requires-Dist: types-appdirs<2,>=1; extra == 'dev'
Requires-Dist: types-filelock<4,>=3; extra == 'dev'
Requires-Dist: types-pytz<2026,>=2025; extra == 'dev'
Requires-Dist: types-tabulate<1,>=0; extra == 'dev'
Requires-Dist: types-tqdm<5,>=4; extra == 'dev'
Requires-Dist: uv<1,>=0; extra == 'dev'
